{"related_usc": [{"number": "1622", "detail": "(d)", "title": "50"}], "title": "PRESIDENTIAL MESSAGES", "content": [{"kind": "linebreak", "speaker_bioguide": null, "text": "                                 ______\n\nREPORT RELATIVE TO THE CONTINUATION OF THE NATIONAL EMERGENCY THAT WAS \nORIGINALLY DECLARED IN EXECUTIVE ORDER 13712 OF NOVEMBER 22, 2015, WITH ", "turn": -1, "speaker": "None", "itemno": 0}, {"kind": "title", "speaker_bioguide": null, "text": "                       RESPECT TO BURUNDI--PM 19\n\n  The PRESIDING OFFICER laid before the Senate the following message \nfrom the President of the United States, together with an accompanying \nreport which was referred to the Committee on Banking, Housing, and \nUrban Affairs.\n\nTo the Congress of the United States:\n  Section 202(d) of the National Emergencies Act (50 U.S.C. 1622(d)) \nprovides for the automatic termination of a national emergency unless, \nwithin 90 days before the anniversary date of its declaration, the \nPresident publishes in the Federal Register and transmits to the \nCongress a notice stating that the emergency is to continue in effect \nbeyond the anniversary date. In accordance with this provision, I have \nsent to the Federal Register for publication the enclosed notice \nstating that the national emergency declared in Executive Order 13712 \nof November 22, 2015, with respect to the situation in Burundi, is to \ncontinue in effect beyond November 22, 2017.\n  The situation in Burundi, which has been marked by killing and other \nviolence against civilians, unrest, the incitement of violence, and \nsignificant political repression, and which threatens the peace, \nsecurity, and stability of Burundi and the region, continues to pose an \nunusual and extraordinary threat to the national security and foreign \npolicy of the United States. For this reason, I have determined that it \nis necessary to continue the national emergency declared in Executive \nOrder 13712 with respect to the situation in Burundi.\n                                                     Donald J. Trump.  \nThe White House, November 6, 2017.\n", "turn": -1, "speaker": "None", "itemno": 1}, {"kind": "linebreak", "speaker_bioguide": null, "text": "                          ____________________\n\n\n", "turn": -1, "speaker": "None", "itemno": 2}], "header": {"chamber": "Senate", "num": "180", "extension": false, "year": "2017", "vol": "163", "pages": "S7014", "wkday": "Monday", "day": "6", "month": "November"}, "doc_title": "PRESIDENTIAL MESSAGES", "id": "CREC-2017-11-06-pt1-PgS7014-4"}