{"content": [{"text": "  The Chaplain, the Reverend Patrick J. Conroy, offered the following \nprayer:\n  Gracious and merciful God, we give You thanks for giving us another \nday.\n  In this Chamber, where the people's House gathers, we pause to offer \nYou gratitude for the gift of this good land on which we live and for \nthis great Nation which You have inspired in developing over so many \nyears. Continue to inspire the American people, that through the \ndifficulties of these days we might keep liberty and justice alive in \nour Nation and in the world.\n  Bless, in a special way, all of our veterans tomorrow and throughout \nthis weekend.\n  Give to us and all people a vivid sense of Your presence, that we may \nlearn to understand each other, to respect each other, to work with \neach other, to live with each other, and to do good to each other. So \nshall we make our Nation great in goodness and good in its greatness.\n  May all that is done this day be for Your greater honor and glory.\n  Amen.\n", "kind": "Unknown", "speaker": "Unknown", "itemno": 0, "turn": -1}, {"kind": "linebreak", "speaker_bioguide": null, "text": "                          ____________________\n\n\n", "turn": -1, "speaker": "None", "itemno": 1}], "header": {"chamber": "House", "num": "184", "extension": false, "year": "2017", "vol": "163", "pages": "H9137", "wkday": "Friday", "day": "10", "month": "November"}, "doc_title": "PRAYER", "id": "CREC-2017-11-10-pt1-PgH9137-3", "title": "PRAYER"}