{"content": [{"kind": "linebreak", "speaker_bioguide": null, "text": "                                 ______\n", "turn": -1, "speaker": "None", "itemno": 0}, {"kind": "title", "speaker_bioguide": null, "text": "                        HON. JOHN J. DUNCAN, JR.\n\n                              of tennessee\n\n                    in the house of representatives\n\n                       Monday, November 13, 2017\n", "turn": -1, "speaker": "None", "itemno": 1}, {"kind": "speech", "speaker_bioguide": "D000533", "text": "  Mr. DUNCAN of Tennessee. Mr. Speaker, a distinguished business owner \nand close friend of mine from my district, Larry G. Cox, will be \nhonored by the North Knoxville Business and Professional Association at \nan event that benefits the Boys and Girls Clubs of Tennessee Valley on \nNovember 14th 2017.\n  Larry has one of the biggest hearts of all the people I have known in \nmy lifetime. Larry has served the people of Knoxville for many years by \ngiving his time and effort to the Emerald Youth Foundation, Kiwanis \nClub, and his church. He also helped make our city a better place \nthrough his tenure as a Knoxville city councilman for two decades.\n  Father of Shane and Brooke, Grandfather of Brielle and Kingston, and \nHusband of Brenda, Larry Cox has created a legacy that few can\n\n\nmatch, and he has touched thousands of people's lives in good and \npositive ways.\n  His passion for promoting a connected community focused on the \nsuccess of our youth has helped many young people who are faced with \nchallenging life situations with little hope in their lives.\n  His dedication to fundraising for the Boys and Girls Clubs has helped \nto provide resources to make the lives of many young people better \nthrough their renewed sense of self, ability to participate in sports, \nand boost in self-confidence.\n  Mr. Speaker, I hope my colleagues will join me in recognizing the \nimpact Larry Cox has made on so many lives through his selflessness and \ndevotion to others. This Nation is a much better place because of the \nlife he has led.\n", "turn": 0, "speaker": "Mr. DUNCAN of Tennessee", "itemno": 2}, {"kind": "linebreak", "speaker_bioguide": null, "text": "                          ____________________\n\n\n", "turn": -1, "speaker": "None", "itemno": 3}], "header": {"chamber": "House", "num": "185", "extension": true, "year": "2017", "vol": "163", "pages": "E1555-E1556", "wkday": "Monday", "day": "13", "month": "November"}, "doc_title": "RECOGNIZING LARRY G. COX", "id": "CREC-2017-11-13-pt1-PgE1555-5", "title": "RECOGNIZING LARRY G. COX"}