{"content": [{"text": "           2017 WOMAN OF THE YEAR AWARD WINNER--SHEILA ALLEN\n", "kind": "Unknown", "speaker": "Unknown", "itemno": 0, "turn": -1}, {"kind": "linebreak", "speaker_bioguide": null, "text": "                                 ______\n", "turn": -1, "speaker": "None", "itemno": 1}, {"kind": "title", "speaker_bioguide": null, "text": "                          HON. JOHN GARAMENDI\n\n                             of california\n\n                    in the house of representatives\n\n                       Tuesday, November 7, 2017\n", "turn": -1, "speaker": "None", "itemno": 2}, {"kind": "speech", "speaker_bioguide": "G000559", "text": "  Mr. GARAMENDI. Mr. Speaker, I rise today to recognize Sheila Allen, a \nproven leader in the Davis, California community who embodies the \nqualities of a true public servant. Sheila is currently the Executive \nDirector of the Yolo Healthy Aging Alliance. She has been instrumental \nin building an organization that serves as a vital voice for older \nadults in Yolo County and elected officials and community leaders \nconsider her the expert in addressing senior issues. Sheila is credited \nwith organizing the 2010 Aging Summit that recognized the need for \nsustained attention of older adults. Her leadership has enhanced the \nlives of countless older adults in Yolo County through educational \nprograms, collaboration with over 80 providers of older adult services \nand is a faithful advocate for needed programs and services at every \nlevel of government.\n   Working alongside County Supervisor Provenza, Sheila was \ninstrumental in helping to advocate for a new Adult Day Health Care \nCenter in Woodland as well as a Memory Center in Davis. Sheila also \nadvocated for legislation to protect seniors from abuse and provide \ngreater access to services in the community. She is currently working \non a similar project in Winters, California.\n   Sheila's community involvement includes, Trustee, Davis Unified \nSchool District, Board Member, First Five Yolo, Board of Director, \nExplorit Science Center, Board of Governors, Agency on Aging, Board of \nDirectors, American Nurses Association, Board of Director, Golden State \nNursing Foundation, Advisory Committee, Yolo County Home Supportive \nServices, Member, Yolo County Health Council, Member, City of Davis \nHuman Relations\n\n\nCommission, and Advisory Committee, Unitrans. Sheila holds a B.S. in \nNursing from University of Wisconsin, Masters and a PhD in Nursing from \nUniversity of San Francisco.\n", "turn": 0, "speaker": "Mr. GARAMENDI", "itemno": 3}, {"kind": "linebreak", "speaker_bioguide": null, "text": "                          ____________________\n\n\n", "turn": -1, "speaker": "None", "itemno": 4}], "header": {"chamber": "House", "num": "181", "extension": true, "year": "2017", "vol": "163", "pages": "E1522-E1523", "wkday": "Tuesday", "day": "7", "month": "November"}, "doc_title": "2017 WOMAN OF THE YEAR AWARD WINNER--SHEILA ALLEN", "id": "CREC-2017-11-07-pt1-PgE1522-5", "title": null}