{"content": [{"kind": "linebreak", "speaker_bioguide": null, "text": "                                 ______\n", "turn": -1, "speaker": "None", "itemno": 0}, {"kind": "title", "speaker_bioguide": null, "text": "                            HON. DAVID YOUNG\n\n                                of iowa\n\n                    in the house of representatives\n\n                       Thursday, November 2, 2017\n", "turn": -1, "speaker": "None", "itemno": 1}, {"kind": "speech", "speaker_bioguide": "Y000066", "text": "  Mr. YOUNG of Iowa. Mr. Speaker, I rise today to recognize and \ncongratulate Mark Hillenbrand of West Des Moines, Iowa for being named \none of West Des Moines Chamber's Citizens of the Year for 2017.\n  The West Des Moines Chamber every year recognizes a Citizen of the \nYear, a community member who ``demonstrates an unparalleled dedication \nto service and general betterment of the community.'' Mark is a \nClinical Social Worker who owns a private practice in Des Moines. Over \nthe past year, Mark, along with Valley High School Associate Principal \nDavid Maxwell, helped to organize several West Des Moines equity, \ndiversity and multicultural discussions, bringing together the \ncommunity and students to tackle educational inequality and ensure that \nall students have equal opportunities for a quality education.\n  Mr. Speaker, I am honored to represent community leaders like Mark in \nthe United States Congress and it is with great pride that I recognize \nhim today. I ask that my colleagues in the United States House of \nRepresentatives join me in congratulating Mark for this outstanding \nrecognition and in wishing him nothing but continued success.\n", "turn": 0, "speaker": "Mr. YOUNG of Iowa", "itemno": 2}, {"kind": "linebreak", "speaker_bioguide": null, "text": "                          ____________________\n\n\n", "turn": -1, "speaker": "None", "itemno": 3}], "header": {"chamber": "House", "num": "178", "extension": true, "year": "2017", "vol": "163", "pages": "E1490", "wkday": "Thursday", "day": "2", "month": "November"}, "doc_title": "TRIBUTE TO MARK HILLENBRAND", "id": "CREC-2017-11-02-pt1-PgE1490-2", "title": "TRIBUTE TO MARK HILLENBRAND"}